tepet/__init__.py
tepet/timer.py
tepet-0.1.1.dist-info/LICENSE
tepet-0.1.1.dist-info/WHEEL
tepet-0.1.1.dist-info/METADATA
tepet-0.1.1.dist-info/RECORD
