Metadata-Version: 2.1
Name: tepet
Version: 0.1.1
Summary: Small timing tool to run performance analysis
Home-page: https://github.com/toshakins/tepet
Author: Anton Ovinnikov
Author-email: toshakins@gmail.com
Requires-Python: >= 3.7
Classifier: License :: OSI Approved :: MIT License
